semgrep_search/__init__.py
semgrep_search/__main__.py
semgrep_search/const.py
semgrep_search/database.py
semgrep_search/inspection.py
semgrep_search/main.py
semgrep_search/run.py
semgrep_search/runconfig.py
semgrep_search/search.py
semgrep_search/semgrep.py
semgrep_search/utils.py
semgrep_search-1.1.3.dist-info/METADATA
semgrep_search-1.1.3.dist-info/WHEEL
semgrep_search-1.1.3.dist-info/entry_points.txt
semgrep_search-1.1.3.dist-info/licenses/COPYING
semgrep_search-1.1.3.dist-info/RECORD
