Metadata-Version: 2.4
Name: semgrep-search
Version: 1.1.3
Summary: A tool to generate a custom Semgrep ruleset from multiple sources
Project-URL: Homepage, https://github.com/hnzlmnn/semgrep-search
Author-email: Malte Heinzelmann <malte@cybaer.ninja>
License-Expression: GPL-3.0-or-later
License-File: COPYING
Requires-Python: >=3.8
Requires-Dist: asyncio<4,>=3.4.3
Requires-Dist: babel<3,>=2.17.0
Requires-Dist: base58<3,>=2.1.1
Requires-Dist: oras<0.3,>=0.2.25
Requires-Dist: pyyaml<7,>=6.0.2
Requires-Dist: requests<3,>=2.32.3
Requires-Dist: rich<14,>=13.9.4
Requires-Dist: ruamel-yaml<0.19,>=0.18.10
Requires-Dist: semver<4,>=3.0.4
Requires-Dist: tinydb<5,>=4.8.2
Requires-Dist: tomli<3,>=2.2.1
